docker_scry/__init__.py
docker_scry/__main__.py
docker_scry/defs.py
docker_scry/scry.py
docker_scry/util.py
docker_scry-0.1.0.dist-info/METADATA
docker_scry-0.1.0.dist-info/WHEEL
docker_scry-0.1.0.dist-info/entry_points.txt
docker_scry-0.1.0.dist-info/licenses/LICENSES/BSD-2-Clause.txt
docker_scry-0.1.0.dist-info/RECORD
